dagster_mysql/__init__.py
dagster_mysql/py.typed
dagster_mysql/storage.py
dagster_mysql/utils.py
dagster_mysql/version.py
dagster_mysql/alembic/__init__.py
dagster_mysql/alembic/alembic.ini
dagster_mysql/event_log/__init__.py
dagster_mysql/event_log/event_log.py
dagster_mysql/run_storage/__init__.py
dagster_mysql/run_storage/run_storage.py
dagster_mysql/schedule_storage/__init__.py
dagster_mysql/schedule_storage/schedule_storage.py
dagster_mysql-1.0.5.dist-info/LICENSE
dagster_mysql-1.0.5.dist-info/METADATA
dagster_mysql-1.0.5.dist-info/WHEEL
dagster_mysql-1.0.5.dist-info/top_level.txt
dagster_mysql-1.0.5.dist-info/RECORD
